Metadata-Version: 2.1
Name: curse-app-api
Version: 0.0.4
Summary: Cuseforge App API
Home-page: https://github.com/CyberSteve777/CurseAppAPI
Author: CyberSteve777
License: UNKNOWN
Download-URL: https://github.com/CyberSteve777/CurseAppAPI/releases
Keywords: python,minecraft,curseforge
Platform: UNKNOWN
Classifier: Intended Audience :: Developers
Classifier: License :: OSI Approved :: GNU General Public License v3 (GPLv3)
Classifier: Programming Language :: Python :: 3
Classifier: Programming Language :: Python :: 3.6
Classifier: Programming Language :: Python :: 3.7
Classifier: Programming Language :: Python :: 3.8
Classifier: Programming Language :: Python :: 3.9
Classifier: Operating System :: Microsoft :: Windows
Requires-Python: >=3.6
License-File: LICENSE
